pymt5/__init__.py
pymt5/pymt5.py
pymt5-1.3.0.dist-info/LICENSE.txt
pymt5-1.3.0.dist-info/METADATA
pymt5-1.3.0.dist-info/WHEEL
pymt5-1.3.0.dist-info/top_level.txt
pymt5-1.3.0.dist-info/RECORD
