Metadata-Version: 2.1
Name: pymt5
Version: 1.3.0
Summary: Python API for MetaTrader 5 gateways
Home-page: https://github.com/devcartel/pymt5
Author: DevCartel
Author-email: support@devcartel.com
License: MIT
Keywords: metatrader,metaquotes,mt5,gateway,api,python
Platform: UNKNOWN
Classifier: Development Status :: 5 - Production/Stable
Classifier: Intended Audience :: Developers
Classifier: Topic :: Software Development :: Build Tools
Classifier: License :: OSI Approved :: MIT License
Classifier: Programming Language :: Python :: 2
Classifier: Programming Language :: Python :: 2.7
Classifier: Programming Language :: Python :: 3
Classifier: Programming Language :: Python :: 3.4
Classifier: Programming Language :: Python :: 3.5
Classifier: Programming Language :: Python :: 3.6
Classifier: Programming Language :: Python :: 3.7
